polyphy/polyphy.py
polyphy/core/common.py
polyphy/core/discrete2D.py
polyphy/core/discrete3D.py
polyphy/kernel/common.py
polyphy/kernel/discrete2D.py
polyphy/kernel/discrete3D.py
polyphy/pipelines/common.py
polyphy/pipelines/discrete2D.py
polyphy/pipelines/discrete3D.py
polyphy/utils/cli_helper.py
polyphy/utils/gui_helper.py
polyphy/utils/logger.py
polyphy_testing-0.0.2.dist-info/LICENSE
polyphy_testing-0.0.2.dist-info/METADATA
polyphy_testing-0.0.2.dist-info/WHEEL
polyphy_testing-0.0.2.dist-info/entry_points.txt
polyphy_testing-0.0.2.dist-info/top_level.txt
polyphy_testing-0.0.2.dist-info/RECORD
