Metadata-Version: 2.1
Name: polyphy-testing
Version: 0.0.2
Summary: description for polyphy testing
Home-page: https://github.com/PolyPhyHub/PolyPhy
Author: Oskar Elek
Author-email: author_name <author@example.com>
Maintainer-email: maintainers_name <maintainers@example.com>
License: MIT License
Project-URL: Documentation, https://github.com/PolyPhyHub/PolyPhy
Project-URL: Source, https://github.com/PolyPhyHub/PolyPhy
Keywords: polyphy
Platform: any
Classifier: Development Status :: 4 - Beta
Classifier: Programming Language :: Python
Requires-Python: >=3.7
License-File: LICENSE
Requires-Dist: pytest
Requires-Dist: pytest-cov
Requires-Dist: importlib-metadata ; python_version < "3.8"
Provides-Extra: testing
Requires-Dist: setuptools ; extra == 'testing'
Requires-Dist: pytest ; extra == 'testing'
Requires-Dist: pytest-cov ; extra == 'testing'
